showy/__init__.py
showy/_showy.py
showy/preprocess_utils.py
showy/schema.yaml
showy/validation.py
showy-0.1.5.dist-info/LICENSE
showy-0.1.5.dist-info/METADATA
showy-0.1.5.dist-info/WHEEL
showy-0.1.5.dist-info/top_level.txt
showy-0.1.5.dist-info/RECORD
