Metadata-Version: 2.1
Name: showy
Version: 0.1.5
Summary: Helper for matplotlib subplots.
Home-page: https://gitlab.com/cerfacs/showy
Author: CoopTeam-CERFACS
Author-email: coop@cerfacs.com
Project-URL: Homepage, https://gitlab.com/cerfacs/showy
Project-URL: Documentation, https://showy.readthedocs.io/en/latest/
Project-URL: Bug Tracker, https://gitlab.com/cerfacs/showy/-/issues
Keywords: declarative visualization,matplotlib
Classifier: Programming Language :: Python :: 3.7
Classifier: Programming Language :: Python :: 3.8
Classifier: Programming Language :: Python :: 3.9
Classifier: Programming Language :: Python :: 3.10
Classifier: License :: OSI Approved :: MIT License
Classifier: Topic :: Scientific/Engineering :: Visualization
Requires-Python: >=3.7
Provides-Extra: tests
License-File: LICENSE
